lymt/__init__.py
lymt/prompt.py
lymt/chat/__init__.py
lymt/chat/anthropic_chat.py
lymt/chat/ollama_chat.py
lymt/chat/openai_chat.py
lymt/models/__init__.py
lymt/models/anthropic_model.py
lymt/models/ollama_model.py
lymt/models/openai_model.py
lymt/prompt/o1-heavy.txt
lymt/prompt/o1-light.txt
lymt/prompt/thinking-claude.txt
lymt-0.1.1.dist-info/LICENSE
lymt-0.1.1.dist-info/METADATA
lymt-0.1.1.dist-info/WHEEL
lymt-0.1.1.dist-info/top_level.txt
lymt-0.1.1.dist-info/RECORD
