Metadata-Version: 2.1
Name: lymt
Version: 0.1.1
Summary: Let Your Model Think
Home-page: https://github.com/GreenScreen410/lymt
Author: GreenScreen410
Author-email: pauljjang410@gmail.com
Maintainer: GreenScreen410
Maintainer-email: pauljjang410@gmail.com
License: MIT
Keywords: llm,machine learning,deep learning,ai,openai,claude,prompt,chatgpt,cot
License-File: LICENSE
Requires-Dist: openai>=1.56.0
Requires-Dist: anthropic>=0.40.0
Requires-Dist: ollama>=0.4.2
